vtb_secret_utils/__init__.py
vtb_secret_utils/cache.py
vtb_secret_utils/utils.py
vtb_secret_utils/vault.py
vtb_secret_utils-0.0.2.dist-info/METADATA
vtb_secret_utils-0.0.2.dist-info/WHEEL
vtb_secret_utils-0.0.2.dist-info/top_level.txt
vtb_secret_utils-0.0.2.dist-info/RECORD
