Metadata-Version: 2.1
Name: vtb-secret-utils
Version: 0.0.2
Summary: Secret utils
Author: VTB python team
Author-email: python.team@vtb.ru
Keywords: python,microservices,utils,http
Classifier: Programming Language :: Python :: 3.8
Classifier: Operating System :: OS Independent
Requires-Python: >=3.8
Requires-Dist: hvac
Provides-Extra: test
Requires-Dist: pytest ; extra == 'test'
Requires-Dist: pytest-cov ; extra == 'test'
Requires-Dist: pytest-aiohttp ; extra == 'test'
Requires-Dist: pytest-mock ; extra == 'test'
Requires-Dist: pylint ; extra == 'test'
Requires-Dist: pytest-dotenv ; extra == 'test'
Requires-Dist: envparse ; extra == 'test'
Requires-Dist: asynctest ; extra == 'test'
